read_log/__init__.py
read_log/apps.py
read_log/models.py
read_log/view_mixins.py
read_log/migrations/0001_initial.py
read_log/migrations/__init__.py
django_read_log-0.80.dist-info/LICENSE
django_read_log-0.80.dist-info/METADATA
django_read_log-0.80.dist-info/WHEEL
django_read_log-0.80.dist-info/top_level.txt
django_read_log-0.80.dist-info/RECORD
