Metadata-Version: 2.1
Name: django-read-log
Version: 0.80
Summary: Read log audit for django 
Home-page: https://www.django-rest-framework.org/
Author: Mikkel Aleister Clausen
Author-email: mac@magenta.dk
License: MIT
Project-URL: Source, https://github.com/magenta-aps/django-read-log
Project-URL: Company, https://www.magenta.dk/
Platform: UNKNOWN
Classifier: Development Status :: 5 - Production/Stable
Classifier: Environment :: Web Environment
Classifier: Framework :: Django
Classifier: Framework :: Django :: 2.2
Classifier: Framework :: Django :: 3.0
Classifier: Intended Audience :: Developers
Classifier: License :: OSI Approved :: MIT License
Classifier: Operating System :: OS Independent
Classifier: Programming Language :: Python
Classifier: Programming Language :: Python :: 3
Classifier: Programming Language :: Python :: 3.5
Classifier: Programming Language :: Python :: 3.6
Classifier: Programming Language :: Python :: 3.7
Classifier: Programming Language :: Python :: 3.8
Classifier: Programming Language :: Python :: 3 :: Only
Classifier: Topic :: Internet :: WWW/HTTP
Requires-Python: >=3.5
Requires-Dist: django (>=2.2)
